<?xml version="1.0" encoding="utf-8"?><toc><breadcrumbs><li><a href="08117695-9afd-4bf2-ac47-ded61324cc18.htm">Docs</a></li></breadcrumbs><tocItems><li><a id="08117695-9afd-4bf2-ac47-ded61324cc18" href="08117695-9afd-4bf2-ac47-ded61324cc18.htm">Welcome to the [TODO: Add project name]</a></li><li><a id="153f08f6-7d72-4c45-8517-37f1c342cbdc" class="has-submenu" href="153f08f6-7d72-4c45-8517-37f1c342cbdc.htm"><span data-tocFile="../toc/IDB.xml" class="icon toggle" onclick="ToggleExpandCollapse(this); return false;"><i class="fa fa-angle-right"> </i></span>Version History</a><ul class="toc-menu is-hidden"> </ul></li><li><a id="ff2948b1-49df-8d4c-ca27-865d6149c167" class="has-submenu" href="ff2948b1-49df-8d4c-ca27-865d6149c167.htm"><span data-tocFile="../toc/IDC.xml" class="icon toggle" onclick="ToggleExpandCollapse(this); return false;"><i class="fa fa-angle-right"> </i></span>Pres<wbr />Ando<wbr />Clothes<wbr />Shop</a><ul class="toc-menu is-hidden"> </ul></li><li><a id="2925f51d-c1ca-d244-88fb-610fc359cab5" class="has-submenu" href="2925f51d-c1ca-d244-88fb-610fc359cab5.htm"><span data-tocFile="../toc/IDD.xml" class="icon toggle" onclick="ToggleExpandCollapse(this); return false;"><i class="fa fa-angle-right"> </i></span>Pres<wbr />Ando<wbr />Clothes<wbr />Shop.<wbr />Areas.<wbr />Identity.<wbr />Pages</a><ul class="toc-menu is-hidden"> </ul></li><li><a id="bbca6733-ac4c-eb6c-33b0-e15f36bf8184" class="has-submenu" href="bbca6733-ac4c-eb6c-33b0-e15f36bf8184.htm"><span data-tocFile="../toc/IDE.xml" class="icon toggle" onclick="ToggleExpandCollapse(this); return false;"><i class="fa fa-angle-right"> </i></span>Pres<wbr />Ando<wbr />Clothes<wbr />Shop.<wbr />Areas.<wbr />Identity.<wbr />Pages.<wbr />Account</a><ul class="toc-menu is-hidden"> </ul></li><li><a id="855f47e9-197b-1f86-211d-248c85abd0cf" class="has-submenu" href="855f47e9-197b-1f86-211d-248c85abd0cf.htm"><span data-tocFile="../toc/IDF.xml" class="icon toggle" onclick="ToggleExpandCollapse(this); return false;"><i class="fa fa-angle-right"> </i></span>Pres<wbr />Ando<wbr />Clothes<wbr />Shop.<wbr />Areas.<wbr />Identity.<wbr />Pages.<wbr />Account.<wbr />Manage</a><ul class="toc-menu is-hidden"> </ul></li><li><a id="27b033a2-28db-34bb-213b-dfc901c337e3" class="has-submenu" href="27b033a2-28db-34bb-213b-dfc901c337e3.htm"><span data-tocFile="../toc/IDG.xml" class="icon toggle" onclick="ToggleExpandCollapse(this); return false;"><i class="fa fa-angle-right"> </i></span>Pres<wbr />Ando<wbr />Clothes<wbr />Shop.<wbr />Controllers</a><ul class="toc-menu is-hidden"> </ul></li><li><a id="8abb9176-3471-bee2-a2a7-f9b24254637a" class="has-submenu" href="8abb9176-3471-bee2-a2a7-f9b24254637a.htm"><span data-tocFile="../toc/IDH.xml" class="icon toggle" onclick="ToggleExpandCollapse(this); return false;"><i class="fa fa-angle-right"> </i></span>Pres<wbr />Ando<wbr />Clothes<wbr />Shop.<wbr />Data</a><ul class="toc-menu is-hidden"> </ul></li><li><a id="8343e6b4-7246-c412-ca56-20a07f506138" class="has-submenu" href="8343e6b4-7246-c412-ca56-20a07f506138.htm"><span data-tocFile="../toc/IDI.xml" class="icon toggle" onclick="ToggleExpandCollapse(this); return false;"><i class="fa fa-angle-right"> </i></span>Pres<wbr />Ando<wbr />Clothes<wbr />Shop.<wbr />Migrations</a><ul class="toc-menu is-hidden"> </ul></li><li><a id="b14dfdbb-f812-eba7-71a3-9fd991954de6" class="has-submenu" href="b14dfdbb-f812-eba7-71a3-9fd991954de6.htm"><span data-tocFile="../toc/IDJ.xml" class="icon toggle" onclick="ToggleExpandCollapse(this); return false;"><i class="fa fa-angle-right"> </i></span>Pres<wbr />Ando<wbr />Clothes<wbr />Shop.<wbr />Models</a><ul class="toc-menu is-hidden"> </ul></li><li><a id="8ac52597-1bb3-4d93-2aad-8a03e5b0ae09" class="has-submenu" href="8ac52597-1bb3-4d93-2aad-8a03e5b0ae09.htm"><span data-tocFile="../toc/IDK.xml" class="icon toggle" onclick="ToggleExpandCollapse(this); return false;"><i class="fa fa-angle-right"> </i></span>Pres<wbr />Ando<wbr />Clothes<wbr />Shop.<wbr />Services</a><ul class="toc-menu is-hidden"> </ul></li><li><a id="d46706a3-f75b-88c3-180b-4f52959ddc87" class="has-submenu" href="d46706a3-f75b-88c3-180b-4f52959ddc87.htm"><span data-tocFile="../toc/IDL.xml" class="icon toggle" onclick="ToggleExpandCollapse(this); return false;"><i class="fa fa-angle-right"> </i></span>Pres<wbr />Ando<wbr />Clothes<wbr />Shop.<wbr />View<wbr />Model</a><ul class="toc-menu is-hidden"> </ul></li></tocItems></toc>